README
setup.py
helper_uri/__init__.py
helper_uri.egg-info/PKG-INFO
helper_uri.egg-info/SOURCES.txt
helper_uri.egg-info/dependency_links.txt
helper_uri.egg-info/top_level.txt