Metadata-Version: 1.0
Name: helper-uri
Version: 0.4
Summary: URI Helper
Home-page: https://github.com/shuge/helper_uri
Author: Shuge Lee
Author-email: shuge.lee@gmail.com
License: MIT License
Platform: UNKNOWN
